bgfiles/__init__.py
bgfiles/fields.py
bgfiles/http.py
bgfiles/models.py
bgfiles/toolbox.py
bgfiles/views.py
bgfiles/management/__init__.py
bgfiles/management/commands/__init__.py
bgfiles/management/commands/bgfiles.py
bgfiles/migrations/0001_initial.py
bgfiles/migrations/__init__.py
bgfiles/patterns/__init__.py
bgfiles/patterns/base.py
bgfiles/patterns/celery.py
bgfiles/patterns/registry.py
dj_bgfiles-0.6.0.dist-info/DESCRIPTION.rst
dj_bgfiles-0.6.0.dist-info/METADATA
dj_bgfiles-0.6.0.dist-info/RECORD
dj_bgfiles-0.6.0.dist-info/WHEEL
dj_bgfiles-0.6.0.dist-info/metadata.json
dj_bgfiles-0.6.0.dist-info/top_level.txt
