Metadata-Version: 2.0
Name: dj-bgfiles
Version: 0.6.0
Summary: Generate files in the background
Home-page: https://github.com/climapulse/dj-bgfiles
Author: Climapulse NV
Author-email: kevin.wetzels@climapulse.com
License: BSD
Keywords: dj-bgfiles,django
Platform: UNKNOWN
Classifier: Development Status :: 3 - Alpha
Classifier: Framework :: Django
Classifier: Framework :: Django :: 1.8
Classifier: Framework :: Django :: 1.9
Classifier: Intended Audience :: Developers
Classifier: License :: OSI Approved :: BSD License
Classifier: Natural Language :: English
Classifier: Programming Language :: Python :: 2
Classifier: Programming Language :: Python :: 2.7
Classifier: Programming Language :: Python :: 3
Classifier: Programming Language :: Python :: 3.4
Classifier: Programming Language :: Python :: 3.5
